README.md
setup.cfg
setup.py
rest2cmd/__init__.py
rest2cmd/rest2cmd.py
rest2cmd.egg-info/PKG-INFO
rest2cmd.egg-info/SOURCES.txt
rest2cmd.egg-info/dependency_links.txt
rest2cmd.egg-info/requires.txt
rest2cmd.egg-info/top_level.txt